Metadata-Version: 1.1
Name: rgomes-velruse
Version: 1.1.2
Summary: Simplifying third-party authentication for web applications.
Home-page: http://velruse.readthedocs.org/en/latest/index.html
Author: Michael Merickel
Author-email: michael@merickel.org
License: UNKNOWN
Keywords: oauth openid social auth facebook google pyramid rest
Platform: UNKNOWN
Classifier: Intended Audience :: Developers
Classifier: License :: OSI Approved :: MIT License
Classifier: Programming Language :: Python :: 2
Classifier: Programming Language :: Python :: 2.6
Classifier: Programming Language :: Python :: 2.7
Classifier: Topic :: Internet :: WWW/HTTP :: WSGI :: Application
Classifier: Framework :: Pyramid
